<?xml version="1.0" encoding="UTF-8" ?>
<!DOCTYPE mapper PUBLIC "-//mybatis.org//DTD Mapper 3.0//EN" "http://mybatis.org/dtd/mybatis-3-mapper.dtd" >
<mapper namespace="com.business.dao.mapper.projectMapper.SspPremisesMapper" >
  <resultMap id="BaseResultMap" type="com.business.dao.entity.projectEntity.SspPremises" >
    <constructor >
      <idArg column="primary_id" jdbcType="INTEGER" javaType="java.lang.Integer" />
      <arg column="uu_id" jdbcType="VARCHAR" javaType="java.lang.String" />
      <arg column="id" jdbcType="BIGINT" javaType="java.lang.Long" />
      <arg column="name" jdbcType="VARCHAR" javaType="java.lang.String" />
      <arg column="developer" jdbcType="VARCHAR" javaType="java.lang.String" />
      <arg column="developer_id" jdbcType="INTEGER" javaType="java.lang.Integer" />
      <arg column="maintainer" jdbcType="VARCHAR" javaType="java.lang.String" />
      <arg column="maintainer_id" jdbcType="INTEGER" javaType="java.lang.Integer" />
      <arg column="status" jdbcType="CHAR" javaType="java.lang.String" />
      <arg column="type" jdbcType="CHAR" javaType="java.lang.String" />
      <arg column="city" jdbcType="INTEGER" javaType="java.lang.Integer" />
      <arg column="area" jdbcType="INTEGER" javaType="java.lang.Integer" />
      <arg column="management" jdbcType="VARCHAR" javaType="java.lang.String" />
      <arg column="build_num" jdbcType="INTEGER" javaType="java.lang.Integer" />
      <arg column="house_num" jdbcType="INTEGER" javaType="java.lang.Integer" />
      <arg column="in_house_rate" jdbcType="REAL" javaType="java.lang.Float" />
      <arg column="unit_num" jdbcType="INTEGER" javaType="java.lang.Integer" />
      <arg column="address" jdbcType="VARCHAR" javaType="java.lang.String" />
      <arg column="accurate_price" jdbcType="INTEGER" javaType="java.lang.Integer" />
      <arg column="house_price" jdbcType="VARCHAR" javaType="java.lang.String" />
      <arg column="house_price_name" jdbcType="VARCHAR" javaType="java.lang.String" />
      <arg column="rent_price" jdbcType="VARCHAR" javaType="java.lang.String" />
      <arg column="management_price" jdbcType="VARCHAR" javaType="java.lang.String" />
      <arg column="max_layer" jdbcType="INTEGER" javaType="java.lang.Integer" />
      <arg column="in_time" jdbcType="BIGINT" javaType="java.lang.Long" />
      <arg column="sign_elevator_num" jdbcType="INTEGER" javaType="java.lang.Integer" />
      <arg column="management_leader" jdbcType="VARCHAR" javaType="java.lang.String" />
      <arg column="management_leader_phone" jdbcType="VARCHAR" javaType="java.lang.String" />
      <arg column="addtime" jdbcType="INTEGER" javaType="java.lang.Integer" />
      <arg column="addman" jdbcType="VARCHAR" javaType="java.lang.String" />
      <arg column="uptime" jdbcType="INTEGER" javaType="java.lang.Integer" />
      <arg column="upman" jdbcType="VARCHAR" javaType="java.lang.String" />
      <arg column="passtime" jdbcType="INTEGER" javaType="java.lang.Integer" />
      <arg column="passman" jdbcType="VARCHAR" javaType="java.lang.String" />
      <arg column="position_lng" jdbcType="DOUBLE" javaType="java.lang.Double" />
      <arg column="position_lat" jdbcType="DOUBLE" javaType="java.lang.Double" />
      <arg column="img" jdbcType="VARCHAR" javaType="java.lang.String" />
      <arg column="expiration_time" jdbcType="BIGINT" javaType="java.lang.Long" />
      <arg column="parking_num" jdbcType="INTEGER" javaType="java.lang.Integer" />
      <arg column="parking_price" jdbcType="VARCHAR" javaType="java.lang.String" />
      <arg column="cover_num" jdbcType="INTEGER" javaType="java.lang.Integer" />
      <arg column="network_type" jdbcType="VARCHAR" javaType="java.lang.String" />
      <arg column="elevator_num" jdbcType="INTEGER" javaType="java.lang.Integer" />
      <arg column="min_storey" jdbcType="INTEGER" javaType="java.lang.Integer" />
      <arg column="max_storey" jdbcType="INTEGER" javaType="java.lang.Integer" />
      <arg column="total_people" jdbcType="INTEGER" javaType="java.lang.Integer" />
      <arg column="enterprise_num" jdbcType="INTEGER" javaType="java.lang.Integer" />
      <arg column="visitors_flowrate" jdbcType="INTEGER" javaType="java.lang.Integer" />
      <arg column="bo_up_price" jdbcType="VARCHAR" javaType="java.lang.String" />
      <arg column="bo_down_price" jdbcType="VARCHAR" javaType="java.lang.String" />
      <arg column="sign_time" jdbcType="VARCHAR" javaType="java.lang.String" />
      <arg column="building_area" jdbcType="INTEGER" javaType="java.lang.Integer" />
      <arg column="contract_num" jdbcType="VARCHAR" javaType="java.lang.String" />
      <arg column="remark" jdbcType="VARCHAR" javaType="java.lang.String" />
      <arg column="city_code" jdbcType="VARCHAR" javaType="java.lang.String" />
      <arg column="area_code" jdbcType="VARCHAR" javaType="java.lang.String" />
      <arg column="province_code" jdbcType="VARCHAR" javaType="java.lang.String" />
      <arg column="acreage" jdbcType="VARCHAR" javaType="java.lang.String" />
      <arg column="cubage_rate" jdbcType="VARCHAR" javaType="java.lang.String" />
      <arg column="greening_rate" jdbcType="VARCHAR" javaType="java.lang.String" />
      <arg column="building_type" jdbcType="VARCHAR" javaType="java.lang.String" />
      <arg column="overground_parking_num" jdbcType="INTEGER" javaType="java.lang.Integer" />
      <arg column="charging_pile_num" jdbcType="INTEGER" javaType="java.lang.Integer" />
      <arg column="developer_name" jdbcType="VARCHAR" javaType="java.lang.String" />
      <arg column="characteristic" jdbcType="VARCHAR" javaType="java.lang.String" />
      <arg column="deal_date" jdbcType="INTEGER" javaType="java.lang.Integer" />
      <arg column="mix_img" jdbcType="VARCHAR" javaType="java.lang.String" />
      <arg column="developers_name" jdbcType="VARCHAR" javaType="java.lang.String" />
    </constructor>
  </resultMap>
  <resultMap id="ResultMapWithBLOBs" type="com.business.dao.entity.projectEntity.SspPremises" >
    <constructor >
      <idArg column="primary_id" jdbcType="INTEGER" javaType="java.lang.Integer" />
      <arg column="uu_id" jdbcType="VARCHAR" javaType="java.lang.String" />
      <arg column="id" jdbcType="BIGINT" javaType="java.lang.Long" />
      <arg column="name" jdbcType="VARCHAR" javaType="java.lang.String" />
      <arg column="developer" jdbcType="VARCHAR" javaType="java.lang.String" />
      <arg column="developer_id" jdbcType="INTEGER" javaType="java.lang.Integer" />
      <arg column="maintainer" jdbcType="VARCHAR" javaType="java.lang.String" />
      <arg column="maintainer_id" jdbcType="INTEGER" javaType="java.lang.Integer" />
      <arg column="status" jdbcType="CHAR" javaType="java.lang.String" />
      <arg column="type" jdbcType="CHAR" javaType="java.lang.String" />
      <arg column="city" jdbcType="INTEGER" javaType="java.lang.Integer" />
      <arg column="area" jdbcType="INTEGER" javaType="java.lang.Integer" />
      <arg column="management" jdbcType="VARCHAR" javaType="java.lang.String" />
      <arg column="build_num" jdbcType="INTEGER" javaType="java.lang.Integer" />
      <arg column="house_num" jdbcType="INTEGER" javaType="java.lang.Integer" />
      <arg column="in_house_rate" jdbcType="REAL" javaType="java.lang.Float" />
      <arg column="unit_num" jdbcType="INTEGER" javaType="java.lang.Integer" />
      <arg column="address" jdbcType="VARCHAR" javaType="java.lang.String" />
      <arg column="accurate_price" jdbcType="INTEGER" javaType="java.lang.Integer" />
      <arg column="house_price" jdbcType="VARCHAR" javaType="java.lang.String" />
      <arg column="house_price_name" jdbcType="VARCHAR" javaType="java.lang.String" />
      <arg column="rent_price" jdbcType="VARCHAR" javaType="java.lang.String" />
      <arg column="management_price" jdbcType="VARCHAR" javaType="java.lang.String" />
      <arg column="max_layer" jdbcType="INTEGER" javaType="java.lang.Integer" />
      <arg column="in_time" jdbcType="BIGINT" javaType="java.lang.Long" />
      <arg column="sign_elevator_num" jdbcType="INTEGER" javaType="java.lang.Integer" />
      <arg column="management_leader" jdbcType="VARCHAR" javaType="java.lang.String" />
      <arg column="management_leader_phone" jdbcType="VARCHAR" javaType="java.lang.String" />
      <arg column="addtime" jdbcType="INTEGER" javaType="java.lang.Integer" />
      <arg column="addman" jdbcType="VARCHAR" javaType="java.lang.String" />
      <arg column="uptime" jdbcType="INTEGER" javaType="java.lang.Integer" />
      <arg column="upman" jdbcType="VARCHAR" javaType="java.lang.String" />
      <arg column="passtime" jdbcType="INTEGER" javaType="java.lang.Integer" />
      <arg column="passman" jdbcType="VARCHAR" javaType="java.lang.String" />
      <arg column="position_lng" jdbcType="DOUBLE" javaType="java.lang.Double" />
      <arg column="position_lat" jdbcType="DOUBLE" javaType="java.lang.Double" />
      <arg column="img" jdbcType="VARCHAR" javaType="java.lang.String" />
      <arg column="expiration_time" jdbcType="BIGINT" javaType="java.lang.Long" />
      <arg column="parking_num" jdbcType="INTEGER" javaType="java.lang.Integer" />
      <arg column="parking_price" jdbcType="VARCHAR" javaType="java.lang.String" />
      <arg column="cover_num" jdbcType="INTEGER" javaType="java.lang.Integer" />
      <arg column="network_type" jdbcType="VARCHAR" javaType="java.lang.String" />
      <arg column="elevator_num" jdbcType="INTEGER" javaType="java.lang.Integer" />
      <arg column="min_storey" jdbcType="INTEGER" javaType="java.lang.Integer" />
      <arg column="max_storey" jdbcType="INTEGER" javaType="java.lang.Integer" />
      <arg column="total_people" jdbcType="INTEGER" javaType="java.lang.Integer" />
      <arg column="enterprise_num" jdbcType="INTEGER" javaType="java.lang.Integer" />
      <arg column="visitors_flowrate" jdbcType="INTEGER" javaType="java.lang.Integer" />
      <arg column="bo_up_price" jdbcType="VARCHAR" javaType="java.lang.String" />
      <arg column="bo_down_price" jdbcType="VARCHAR" javaType="java.lang.String" />
      <arg column="sign_time" jdbcType="VARCHAR" javaType="java.lang.String" />
      <arg column="building_area" jdbcType="INTEGER" javaType="java.lang.Integer" />
      <arg column="contract_num" jdbcType="VARCHAR" javaType="java.lang.String" />
      <arg column="remark" jdbcType="VARCHAR" javaType="java.lang.String" />
      <arg column="city_code" jdbcType="VARCHAR" javaType="java.lang.String" />
      <arg column="area_code" jdbcType="VARCHAR" javaType="java.lang.String" />
      <arg column="province_code" jdbcType="VARCHAR" javaType="java.lang.String" />
      <arg column="acreage" jdbcType="VARCHAR" javaType="java.lang.String" />
      <arg column="cubage_rate" jdbcType="VARCHAR" javaType="java.lang.String" />
      <arg column="greening_rate" jdbcType="VARCHAR" javaType="java.lang.String" />
      <arg column="building_type" jdbcType="VARCHAR" javaType="java.lang.String" />
      <arg column="overground_parking_num" jdbcType="INTEGER" javaType="java.lang.Integer" />
      <arg column="charging_pile_num" jdbcType="INTEGER" javaType="java.lang.Integer" />
      <arg column="developer_name" jdbcType="VARCHAR" javaType="java.lang.String" />
      <arg column="characteristic" jdbcType="VARCHAR" javaType="java.lang.String" />
      <arg column="deal_date" jdbcType="INTEGER" javaType="java.lang.Integer" />
      <arg column="mix_img" jdbcType="VARCHAR" javaType="java.lang.String" />
      <arg column="developers_name" jdbcType="VARCHAR" javaType="java.lang.String" />
      <arg column="competitive_media" jdbcType="LONGVARCHAR" javaType="java.lang.String" />
    </constructor>
  </resultMap>
  <sql id="Example_Where_Clause" >
    <where >
      <foreach collection="oredCriteria" item="criteria" separator="or" >
        <if test="criteria.valid" >
          <trim prefix="(" suffix=")" prefixOverrides="and" >
            <foreach collection="criteria.criteria" item="criterion" >
              <choose >
                <when test="criterion.noValue" >
                  and ${criterion.condition}
                </when>
                <when test="criterion.singleValue" >
                  and ${criterion.condition} #{criterion.value}
                </when>
                <when test="criterion.betweenValue" >
                  and ${criterion.condition} #{criterion.value} and #{criterion.secondValue}
                </when>
                <when test="criterion.listValue" >
                  and ${criterion.condition}
                  <foreach collection="criterion.value" item="listItem" open="(" close=")" separator="," >
                    #{listItem}
                  </foreach>
                </when>
              </choose>
            </foreach>
          </trim>
        </if>
      </foreach>
    </where>
  </sql>
  <sql id="Update_By_Example_Where_Clause" >
    <where >
      <foreach collection="example.oredCriteria" item="criteria" separator="or" >
        <if test="criteria.valid" >
          <trim prefix="(" suffix=")" prefixOverrides="and" >
            <foreach collection="criteria.criteria" item="criterion" >
              <choose >
                <when test="criterion.noValue" >
                  and ${criterion.condition}
                </when>
                <when test="criterion.singleValue" >
                  and ${criterion.condition} #{criterion.value}
                </when>
                <when test="criterion.betweenValue" >
                  and ${criterion.condition} #{criterion.value} and #{criterion.secondValue}
                </when>
                <when test="criterion.listValue" >
                  and ${criterion.condition}
                  <foreach collection="criterion.value" item="listItem" open="(" close=")" separator="," >
                    #{listItem}
                  </foreach>
                </when>
              </choose>
            </foreach>
          </trim>
        </if>
      </foreach>
    </where>
  </sql>
  <sql id="Base_Column_List" >
    primary_id, uu_id, id, name, developer, developer_id, maintainer, maintainer_id, 
    status, type, city, area, management, build_num, house_num, in_house_rate, unit_num, 
    address, accurate_price, house_price, house_price_name, rent_price, management_price, 
    max_layer, in_time, sign_elevator_num, management_leader, management_leader_phone, 
    addtime, addman, uptime, upman, passtime, passman, position_lng, position_lat, img, 
    expiration_time, parking_num, parking_price, cover_num, network_type, elevator_num, 
    min_storey, max_storey, total_people, enterprise_num, visitors_flowrate, bo_up_price, 
    bo_down_price, sign_time, building_area, contract_num, remark, city_code, area_code, 
    province_code, acreage, cubage_rate, greening_rate, building_type, overground_parking_num, 
    charging_pile_num, developer_name, characteristic, deal_date, mix_img, developers_name
  </sql>
  <sql id="Blob_Column_List" >
    competitive_media
  </sql>
  <select id="selectByExampleWithBLOBs" resultMap="ResultMapWithBLOBs" parameterType="com.business.dao.entity.projectEntity.SspPremisesExample" >
    select
    <if test="distinct" >
      distinct
    </if>
    <include refid="Base_Column_List" />
    ,
    <include refid="Blob_Column_List" />
    from ssp_premises
    <if test="_parameter != null" >
      <include refid="Example_Where_Clause" />
    </if>
    <if test="orderByClause != null" >
      order by ${orderByClause}
    </if>
  </select>
  <select id="selectByExample" resultMap="BaseResultMap" parameterType="com.business.dao.entity.projectEntity.SspPremisesExample" >
    select
    <if test="distinct" >
      distinct
    </if>
    <include refid="Base_Column_List" />
    from ssp_premises
    <if test="_parameter != null" >
      <include refid="Example_Where_Clause" />
    </if>
    <if test="orderByClause != null" >
      order by ${orderByClause}
    </if>
  </select>
  <select id="selectByPrimaryKey" resultMap="ResultMapWithBLOBs" parameterType="java.lang.Integer" >
    select 
    <include refid="Base_Column_List" />
    ,
    <include refid="Blob_Column_List" />
    from ssp_premises
    where primary_id = #{primaryId,jdbcType=INTEGER}
  </select>
  <delete id="deleteByPrimaryKey" parameterType="java.lang.Integer" >
    delete from ssp_premises
    where primary_id = #{primaryId,jdbcType=INTEGER}
  </delete>
  <insert id="insert" parameterType="com.business.dao.entity.projectEntity.SspPremises" >
    insert into ssp_premises (primary_id, uu_id, id, 
      name, developer, developer_id, 
      maintainer, maintainer_id, status, 
      type, city, area, management, 
      build_num, house_num, in_house_rate, 
      unit_num, address, accurate_price, 
      house_price, house_price_name, rent_price, 
      management_price, max_layer, in_time, 
      sign_elevator_num, management_leader, management_leader_phone, 
      addtime, addman, uptime, 
      upman, passtime, passman, 
      position_lng, position_lat, img, 
      expiration_time, parking_num, parking_price, 
      cover_num, network_type, elevator_num, 
      min_storey, max_storey, total_people, 
      enterprise_num, visitors_flowrate, bo_up_price, 
      bo_down_price, sign_time, building_area, 
      contract_num, remark, city_code, 
      area_code, province_code, acreage, 
      cubage_rate, greening_rate, building_type, 
      overground_parking_num, charging_pile_num, 
      developer_name, characteristic, deal_date, 
      mix_img, developers_name, competitive_media
      )
    values (#{primaryId,jdbcType=INTEGER}, #{uuId,jdbcType=VARCHAR}, #{id,jdbcType=BIGINT}, 
      #{name,jdbcType=VARCHAR}, #{developer,jdbcType=VARCHAR}, #{developerId,jdbcType=INTEGER}, 
      #{maintainer,jdbcType=VARCHAR}, #{maintainerId,jdbcType=INTEGER}, #{status,jdbcType=CHAR}, 
      #{type,jdbcType=CHAR}, #{city,jdbcType=INTEGER}, #{area,jdbcType=INTEGER}, #{management,jdbcType=VARCHAR}, 
      #{buildNum,jdbcType=INTEGER}, #{houseNum,jdbcType=INTEGER}, #{inHouseRate,jdbcType=REAL}, 
      #{unitNum,jdbcType=INTEGER}, #{address,jdbcType=VARCHAR}, #{accuratePrice,jdbcType=INTEGER}, 
      #{housePrice,jdbcType=VARCHAR}, #{housePriceName,jdbcType=VARCHAR}, #{rentPrice,jdbcType=VARCHAR}, 
      #{managementPrice,jdbcType=VARCHAR}, #{maxLayer,jdbcType=INTEGER}, #{inTime,jdbcType=BIGINT}, 
      #{signElevatorNum,jdbcType=INTEGER}, #{managementLeader,jdbcType=VARCHAR}, #{managementLeaderPhone,jdbcType=VARCHAR}, 
      #{addtime,jdbcType=INTEGER}, #{addman,jdbcType=VARCHAR}, #{uptime,jdbcType=INTEGER}, 
      #{upman,jdbcType=VARCHAR}, #{passtime,jdbcType=INTEGER}, #{passman,jdbcType=VARCHAR}, 
      #{positionLng,jdbcType=DOUBLE}, #{positionLat,jdbcType=DOUBLE}, #{img,jdbcType=VARCHAR}, 
      #{expirationTime,jdbcType=BIGINT}, #{parkingNum,jdbcType=INTEGER}, #{parkingPrice,jdbcType=VARCHAR}, 
      #{coverNum,jdbcType=INTEGER}, #{networkType,jdbcType=VARCHAR}, #{elevatorNum,jdbcType=INTEGER}, 
      #{minStorey,jdbcType=INTEGER}, #{maxStorey,jdbcType=INTEGER}, #{totalPeople,jdbcType=INTEGER}, 
      #{enterpriseNum,jdbcType=INTEGER}, #{visitorsFlowrate,jdbcType=INTEGER}, #{boUpPrice,jdbcType=VARCHAR}, 
      #{boDownPrice,jdbcType=VARCHAR}, #{signTime,jdbcType=VARCHAR}, #{buildingArea,jdbcType=INTEGER}, 
      #{contractNum,jdbcType=VARCHAR}, #{remark,jdbcType=VARCHAR}, #{cityCode,jdbcType=VARCHAR}, 
      #{areaCode,jdbcType=VARCHAR}, #{provinceCode,jdbcType=VARCHAR}, #{acreage,jdbcType=VARCHAR}, 
      #{cubageRate,jdbcType=VARCHAR}, #{greeningRate,jdbcType=VARCHAR}, #{buildingType,jdbcType=VARCHAR}, 
      #{overgroundParkingNum,jdbcType=INTEGER}, #{chargingPileNum,jdbcType=INTEGER}, 
      #{developerName,jdbcType=VARCHAR}, #{characteristic,jdbcType=VARCHAR}, #{dealDate,jdbcType=INTEGER}, 
      #{mixImg,jdbcType=VARCHAR}, #{developersName,jdbcType=VARCHAR}, #{competitiveMedia,jdbcType=LONGVARCHAR}
      )
  </insert>
  <insert id="insertSelective" parameterType="com.business.dao.entity.projectEntity.SspPremises" >
    insert into ssp_premises
    <trim prefix="(" suffix=")" suffixOverrides="," >
      <if test="primaryId != null" >
        primary_id,
      </if>
      <if test="uuId != null" >
        uu_id,
      </if>
      <if test="id != null" >
        id,
      </if>
      <if test="name != null" >
        name,
      </if>
      <if test="developer != null" >
        developer,
      </if>
      <if test="developerId != null" >
        developer_id,
      </if>
      <if test="maintainer != null" >
        maintainer,
      </if>
      <if test="maintainerId != null" >
        maintainer_id,
      </if>
      <if test="status != null" >
        status,
      </if>
      <if test="type != null" >
        type,
      </if>
      <if test="city != null" >
        city,
      </if>
      <if test="area != null" >
        area,
      </if>
      <if test="management != null" >
        management,
      </if>
      <if test="buildNum != null" >
        build_num,
      </if>
      <if test="houseNum != null" >
        house_num,
      </if>
      <if test="inHouseRate != null" >
        in_house_rate,
      </if>
      <if test="unitNum != null" >
        unit_num,
      </if>
      <if test="address != null" >
        address,
      </if>
      <if test="accuratePrice != null" >
        accurate_price,
      </if>
      <if test="housePrice != null" >
        house_price,
      </if>
      <if test="housePriceName != null" >
        house_price_name,
      </if>
      <if test="rentPrice != null" >
        rent_price,
      </if>
      <if test="managementPrice != null" >
        management_price,
      </if>
      <if test="maxLayer != null" >
        max_layer,
      </if>
      <if test="inTime != null" >
        in_time,
      </if>
      <if test="signElevatorNum != null" >
        sign_elevator_num,
      </if>
      <if test="managementLeader != null" >
        management_leader,
      </if>
      <if test="managementLeaderPhone != null" >
        management_leader_phone,
      </if>
      <if test="addtime != null" >
        addtime,
      </if>
      <if test="addman != null" >
        addman,
      </if>
      <if test="uptime != null" >
        uptime,
      </if>
      <if test="upman != null" >
        upman,
      </if>
      <if test="passtime != null" >
        passtime,
      </if>
      <if test="passman != null" >
        passman,
      </if>
      <if test="positionLng != null" >
        position_lng,
      </if>
      <if test="positionLat != null" >
        position_lat,
      </if>
      <if test="img != null" >
        img,
      </if>
      <if test="expirationTime != null" >
        expiration_time,
      </if>
      <if test="parkingNum != null" >
        parking_num,
      </if>
      <if test="parkingPrice != null" >
        parking_price,
      </if>
      <if test="coverNum != null" >
        cover_num,
      </if>
      <if test="networkType != null" >
        network_type,
      </if>
      <if test="elevatorNum != null" >
        elevator_num,
      </if>
      <if test="minStorey != null" >
        min_storey,
      </if>
      <if test="maxStorey != null" >
        max_storey,
      </if>
      <if test="totalPeople != null" >
        total_people,
      </if>
      <if test="enterpriseNum != null" >
        enterprise_num,
      </if>
      <if test="visitorsFlowrate != null" >
        visitors_flowrate,
      </if>
      <if test="boUpPrice != null" >
        bo_up_price,
      </if>
      <if test="boDownPrice != null" >
        bo_down_price,
      </if>
      <if test="signTime != null" >
        sign_time,
      </if>
      <if test="buildingArea != null" >
        building_area,
      </if>
      <if test="contractNum != null" >
        contract_num,
      </if>
      <if test="remark != null" >
        remark,
      </if>
      <if test="cityCode != null" >
        city_code,
      </if>
      <if test="areaCode != null" >
        area_code,
      </if>
      <if test="provinceCode != null" >
        province_code,
      </if>
      <if test="acreage != null" >
        acreage,
      </if>
      <if test="cubageRate != null" >
        cubage_rate,
      </if>
      <if test="greeningRate != null" >
        greening_rate,
      </if>
      <if test="buildingType != null" >
        building_type,
      </if>
      <if test="overgroundParkingNum != null" >
        overground_parking_num,
      </if>
      <if test="chargingPileNum != null" >
        charging_pile_num,
      </if>
      <if test="developerName != null" >
        developer_name,
      </if>
      <if test="characteristic != null" >
        characteristic,
      </if>
      <if test="dealDate != null" >
        deal_date,
      </if>
      <if test="mixImg != null" >
        mix_img,
      </if>
      <if test="developersName != null" >
        developers_name,
      </if>
      <if test="competitiveMedia != null" >
        competitive_media,
      </if>
    </trim>
    <trim prefix="values (" suffix=")" suffixOverrides="," >
      <if test="primaryId != null" >
        #{primaryId,jdbcType=INTEGER},
      </if>
      <if test="uuId != null" >
        #{uuId,jdbcType=VARCHAR},
      </if>
      <if test="id != null" >
        #{id,jdbcType=BIGINT},
      </if>
      <if test="name != null" >
        #{name,jdbcType=VARCHAR},
      </if>
      <if test="developer != null" >
        #{developer,jdbcType=VARCHAR},
      </if>
      <if test="developerId != null" >
        #{developerId,jdbcType=INTEGER},
      </if>
      <if test="maintainer != null" >
        #{maintainer,jdbcType=VARCHAR},
      </if>
      <if test="maintainerId != null" >
        #{maintainerId,jdbcType=INTEGER},
      </if>
      <if test="status != null" >
        #{status,jdbcType=CHAR},
      </if>
      <if test="type != null" >
        #{type,jdbcType=CHAR},
      </if>
      <if test="city != null" >
        #{city,jdbcType=INTEGER},
      </if>
      <if test="area != null" >
        #{area,jdbcType=INTEGER},
      </if>
      <if test="management != null" >
        #{management,jdbcType=VARCHAR},
      </if>
      <if test="buildNum != null" >
        #{buildNum,jdbcType=INTEGER},
      </if>
      <if test="houseNum != null" >
        #{houseNum,jdbcType=INTEGER},
      </if>
      <if test="inHouseRate != null" >
        #{inHouseRate,jdbcType=REAL},
      </if>
      <if test="unitNum != null" >
        #{unitNum,jdbcType=INTEGER},
      </if>
      <if test="address != null" >
        #{address,jdbcType=VARCHAR},
      </if>
      <if test="accuratePrice != null" >
        #{accuratePrice,jdbcType=INTEGER},
      </if>
      <if test="housePrice != null" >
        #{housePrice,jdbcType=VARCHAR},
      </if>
      <if test="housePriceName != null" >
        #{housePriceName,jdbcType=VARCHAR},
      </if>
      <if test="rentPrice != null" >
        #{rentPrice,jdbcType=VARCHAR},
      </if>
      <if test="managementPrice != null" >
        #{managementPrice,jdbcType=VARCHAR},
      </if>
      <if test="maxLayer != null" >
        #{maxLayer,jdbcType=INTEGER},
      </if>
      <if test="inTime != null" >
        #{inTime,jdbcType=BIGINT},
      </if>
      <if test="signElevatorNum != null" >
        #{signElevatorNum,jdbcType=INTEGER},
      </if>
      <if test="managementLeader != null" >
        #{managementLeader,jdbcType=VARCHAR},
      </if>
      <if test="managementLeaderPhone != null" >
        #{managementLeaderPhone,jdbcType=VARCHAR},
      </if>
      <if test="addtime != null" >
        #{addtime,jdbcType=INTEGER},
      </if>
      <if test="addman != null" >
        #{addman,jdbcType=VARCHAR},
      </if>
      <if test="uptime != null" >
        #{uptime,jdbcType=INTEGER},
      </if>
      <if test="upman != null" >
        #{upman,jdbcType=VARCHAR},
      </if>
      <if test="passtime != null" >
        #{passtime,jdbcType=INTEGER},
      </if>
      <if test="passman != null" >
        #{passman,jdbcType=VARCHAR},
      </if>
      <if test="positionLng != null" >
        #{positionLng,jdbcType=DOUBLE},
      </if>
      <if test="positionLat != null" >
        #{positionLat,jdbcType=DOUBLE},
      </if>
      <if test="img != null" >
        #{img,jdbcType=VARCHAR},
      </if>
      <if test="expirationTime != null" >
        #{expirationTime,jdbcType=BIGINT},
      </if>
      <if test="parkingNum != null" >
        #{parkingNum,jdbcType=INTEGER},
      </if>
      <if test="parkingPrice != null" >
        #{parkingPrice,jdbcType=VARCHAR},
      </if>
      <if test="coverNum != null" >
        #{coverNum,jdbcType=INTEGER},
      </if>
      <if test="networkType != null" >
        #{networkType,jdbcType=VARCHAR},
      </if>
      <if test="elevatorNum != null" >
        #{elevatorNum,jdbcType=INTEGER},
      </if>
      <if test="minStorey != null" >
        #{minStorey,jdbcType=INTEGER},
      </if>
      <if test="maxStorey != null" >
        #{maxStorey,jdbcType=INTEGER},
      </if>
      <if test="totalPeople != null" >
        #{totalPeople,jdbcType=INTEGER},
      </if>
      <if test="enterpriseNum != null" >
        #{enterpriseNum,jdbcType=INTEGER},
      </if>
      <if test="visitorsFlowrate != null" >
        #{visitorsFlowrate,jdbcType=INTEGER},
      </if>
      <if test="boUpPrice != null" >
        #{boUpPrice,jdbcType=VARCHAR},
      </if>
      <if test="boDownPrice != null" >
        #{boDownPrice,jdbcType=VARCHAR},
      </if>
      <if test="signTime != null" >
        #{signTime,jdbcType=VARCHAR},
      </if>
      <if test="buildingArea != null" >
        #{buildingArea,jdbcType=INTEGER},
      </if>
      <if test="contractNum != null" >
        #{contractNum,jdbcType=VARCHAR},
      </if>
      <if test="remark != null" >
        #{remark,jdbcType=VARCHAR},
      </if>
      <if test="cityCode != null" >
        #{cityCode,jdbcType=VARCHAR},
      </if>
      <if test="areaCode != null" >
        #{areaCode,jdbcType=VARCHAR},
      </if>
      <if test="provinceCode != null" >
        #{provinceCode,jdbcType=VARCHAR},
      </if>
      <if test="acreage != null" >
        #{acreage,jdbcType=VARCHAR},
      </if>
      <if test="cubageRate != null" >
        #{cubageRate,jdbcType=VARCHAR},
      </if>
      <if test="greeningRate != null" >
        #{greeningRate,jdbcType=VARCHAR},
      </if>
      <if test="buildingType != null" >
        #{buildingType,jdbcType=VARCHAR},
      </if>
      <if test="overgroundParkingNum != null" >
        #{overgroundParkingNum,jdbcType=INTEGER},
      </if>
      <if test="chargingPileNum != null" >
        #{chargingPileNum,jdbcType=INTEGER},
      </if>
      <if test="developerName != null" >
        #{developerName,jdbcType=VARCHAR},
      </if>
      <if test="characteristic != null" >
        #{characteristic,jdbcType=VARCHAR},
      </if>
      <if test="dealDate != null" >
        #{dealDate,jdbcType=INTEGER},
      </if>
      <if test="mixImg != null" >
        #{mixImg,jdbcType=VARCHAR},
      </if>
      <if test="developersName != null" >
        #{developersName,jdbcType=VARCHAR},
      </if>
      <if test="competitiveMedia != null" >
        #{competitiveMedia,jdbcType=LONGVARCHAR},
      </if>
    </trim>
  </insert>
  <update id="updateByExampleSelective" parameterType="map" >
    update ssp_premises
    <set >
      <if test="record.primaryId != null" >
        primary_id = #{record.primaryId,jdbcType=INTEGER},
      </if>
      <if test="record.uuId != null" >
        uu_id = #{record.uuId,jdbcType=VARCHAR},
      </if>
      <if test="record.id != null" >
        id = #{record.id,jdbcType=BIGINT},
      </if>
      <if test="record.name != null" >
        name = #{record.name,jdbcType=VARCHAR},
      </if>
      <if test="record.developer != null" >
        developer = #{record.developer,jdbcType=VARCHAR},
      </if>
      <if test="record.developerId != null" >
        developer_id = #{record.developerId,jdbcType=INTEGER},
      </if>
      <if test="record.maintainer != null" >
        maintainer = #{record.maintainer,jdbcType=VARCHAR},
      </if>
      <if test="record.maintainerId != null" >
        maintainer_id = #{record.maintainerId,jdbcType=INTEGER},
      </if>
      <if test="record.status != null" >
        status = #{record.status,jdbcType=CHAR},
      </if>
      <if test="record.type != null" >
        type = #{record.type,jdbcType=CHAR},
      </if>
      <if test="record.city != null" >
        city = #{record.city,jdbcType=INTEGER},
      </if>
      <if test="record.area != null" >
        area = #{record.area,jdbcType=INTEGER},
      </if>
      <if test="record.management != null" >
        management = #{record.management,jdbcType=VARCHAR},
      </if>
      <if test="record.buildNum != null" >
        build_num = #{record.buildNum,jdbcType=INTEGER},
      </if>
      <if test="record.houseNum != null" >
        house_num = #{record.houseNum,jdbcType=INTEGER},
      </if>
      <if test="record.inHouseRate != null" >
        in_house_rate = #{record.inHouseRate,jdbcType=REAL},
      </if>
      <if test="record.unitNum != null" >
        unit_num = #{record.unitNum,jdbcType=INTEGER},
      </if>
      <if test="record.address != null" >
        address = #{record.address,jdbcType=VARCHAR},
      </if>
      <if test="record.accuratePrice != null" >
        accurate_price = #{record.accuratePrice,jdbcType=INTEGER},
      </if>
      <if test="record.housePrice != null" >
        house_price = #{record.housePrice,jdbcType=VARCHAR},
      </if>
      <if test="record.housePriceName != null" >
        house_price_name = #{record.housePriceName,jdbcType=VARCHAR},
      </if>
      <if test="record.rentPrice != null" >
        rent_price = #{record.rentPrice,jdbcType=VARCHAR},
      </if>
      <if test="record.managementPrice != null" >
        management_price = #{record.managementPrice,jdbcType=VARCHAR},
      </if>
      <if test="record.maxLayer != null" >
        max_layer = #{record.maxLayer,jdbcType=INTEGER},
      </if>
      <if test="record.inTime != null" >
        in_time = #{record.inTime,jdbcType=BIGINT},
      </if>
      <if test="record.signElevatorNum != null" >
        sign_elevator_num = #{record.signElevatorNum,jdbcType=INTEGER},
      </if>
      <if test="record.managementLeader != null" >
        management_leader = #{record.managementLeader,jdbcType=VARCHAR},
      </if>
      <if test="record.managementLeaderPhone != null" >
        management_leader_phone = #{record.managementLeaderPhone,jdbcType=VARCHAR},
      </if>
      <if test="record.addtime != null" >
        addtime = #{record.addtime,jdbcType=INTEGER},
      </if>
      <if test="record.addman != null" >
        addman = #{record.addman,jdbcType=VARCHAR},
      </if>
      <if test="record.uptime != null" >
        uptime = #{record.uptime,jdbcType=INTEGER},
      </if>
      <if test="record.upman != null" >
        upman = #{record.upman,jdbcType=VARCHAR},
      </if>
      <if test="record.passtime != null" >
        passtime = #{record.passtime,jdbcType=INTEGER},
      </if>
      <if test="record.passman != null" >
        passman = #{record.passman,jdbcType=VARCHAR},
      </if>
      <if test="record.positionLng != null" >
        position_lng = #{record.positionLng,jdbcType=DOUBLE},
      </if>
      <if test="record.positionLat != null" >
        position_lat = #{record.positionLat,jdbcType=DOUBLE},
      </if>
      <if test="record.img != null" >
        img = #{record.img,jdbcType=VARCHAR},
      </if>
      <if test="record.expirationTime != null" >
        expiration_time = #{record.expirationTime,jdbcType=BIGINT},
      </if>
      <if test="record.parkingNum != null" >
        parking_num = #{record.parkingNum,jdbcType=INTEGER},
      </if>
      <if test="record.parkingPrice != null" >
        parking_price = #{record.parkingPrice,jdbcType=VARCHAR},
      </if>
      <if test="record.coverNum != null" >
        cover_num = #{record.coverNum,jdbcType=INTEGER},
      </if>
      <if test="record.networkType != null" >
        network_type = #{record.networkType,jdbcType=VARCHAR},
      </if>
      <if test="record.elevatorNum != null" >
        elevator_num = #{record.elevatorNum,jdbcType=INTEGER},
      </if>
      <if test="record.minStorey != null" >
        min_storey = #{record.minStorey,jdbcType=INTEGER},
      </if>
      <if test="record.maxStorey != null" >
        max_storey = #{record.maxStorey,jdbcType=INTEGER},
      </if>
      <if test="record.totalPeople != null" >
        total_people = #{record.totalPeople,jdbcType=INTEGER},
      </if>
      <if test="record.enterpriseNum != null" >
        enterprise_num = #{record.enterpriseNum,jdbcType=INTEGER},
      </if>
      <if test="record.visitorsFlowrate != null" >
        visitors_flowrate = #{record.visitorsFlowrate,jdbcType=INTEGER},
      </if>
      <if test="record.boUpPrice != null" >
        bo_up_price = #{record.boUpPrice,jdbcType=VARCHAR},
      </if>
      <if test="record.boDownPrice != null" >
        bo_down_price = #{record.boDownPrice,jdbcType=VARCHAR},
      </if>
      <if test="record.signTime != null" >
        sign_time = #{record.signTime,jdbcType=VARCHAR},
      </if>
      <if test="record.buildingArea != null" >
        building_area = #{record.buildingArea,jdbcType=INTEGER},
      </if>
      <if test="record.contractNum != null" >
        contract_num = #{record.contractNum,jdbcType=VARCHAR},
      </if>
      <if test="record.remark != null" >
        remark = #{record.remark,jdbcType=VARCHAR},
      </if>
      <if test="record.cityCode != null" >
        city_code = #{record.cityCode,jdbcType=VARCHAR},
      </if>
      <if test="record.areaCode != null" >
        area_code = #{record.areaCode,jdbcType=VARCHAR},
      </if>
      <if test="record.provinceCode != null" >
        province_code = #{record.provinceCode,jdbcType=VARCHAR},
      </if>
      <if test="record.acreage != null" >
        acreage = #{record.acreage,jdbcType=VARCHAR},
      </if>
      <if test="record.cubageRate != null" >
        cubage_rate = #{record.cubageRate,jdbcType=VARCHAR},
      </if>
      <if test="record.greeningRate != null" >
        greening_rate = #{record.greeningRate,jdbcType=VARCHAR},
      </if>
      <if test="record.buildingType != null" >
        building_type = #{record.buildingType,jdbcType=VARCHAR},
      </if>
      <if test="record.overgroundParkingNum != null" >
        overground_parking_num = #{record.overgroundParkingNum,jdbcType=INTEGER},
      </if>
      <if test="record.chargingPileNum != null" >
        charging_pile_num = #{record.chargingPileNum,jdbcType=INTEGER},
      </if>
      <if test="record.developerName != null" >
        developer_name = #{record.developerName,jdbcType=VARCHAR},
      </if>
      <if test="record.characteristic != null" >
        characteristic = #{record.characteristic,jdbcType=VARCHAR},
      </if>
      <if test="record.dealDate != null" >
        deal_date = #{record.dealDate,jdbcType=INTEGER},
      </if>
      <if test="record.mixImg != null" >
        mix_img = #{record.mixImg,jdbcType=VARCHAR},
      </if>
      <if test="record.developersName != null" >
        developers_name = #{record.developersName,jdbcType=VARCHAR},
      </if>
      <if test="record.competitiveMedia != null" >
        competitive_media = #{record.competitiveMedia,jdbcType=LONGVARCHAR},
      </if>
    </set>
    <if test="_parameter != null" >
      <include refid="Update_By_Example_Where_Clause" />
    </if>
  </update>
  <update id="updateByExampleWithBLOBs" parameterType="map" >
    update ssp_premises
    set primary_id = #{record.primaryId,jdbcType=INTEGER},
      uu_id = #{record.uuId,jdbcType=VARCHAR},
      id = #{record.id,jdbcType=BIGINT},
      name = #{record.name,jdbcType=VARCHAR},
      developer = #{record.developer,jdbcType=VARCHAR},
      developer_id = #{record.developerId,jdbcType=INTEGER},
      maintainer = #{record.maintainer,jdbcType=VARCHAR},
      maintainer_id = #{record.maintainerId,jdbcType=INTEGER},
      status = #{record.status,jdbcType=CHAR},
      type = #{record.type,jdbcType=CHAR},
      city = #{record.city,jdbcType=INTEGER},
      area = #{record.area,jdbcType=INTEGER},
      management = #{record.management,jdbcType=VARCHAR},
      build_num = #{record.buildNum,jdbcType=INTEGER},
      house_num = #{record.houseNum,jdbcType=INTEGER},
      in_house_rate = #{record.inHouseRate,jdbcType=REAL},
      unit_num = #{record.unitNum,jdbcType=INTEGER},
      address = #{record.address,jdbcType=VARCHAR},
      accurate_price = #{record.accuratePrice,jdbcType=INTEGER},
      house_price = #{record.housePrice,jdbcType=VARCHAR},
      house_price_name = #{record.housePriceName,jdbcType=VARCHAR},
      rent_price = #{record.rentPrice,jdbcType=VARCHAR},
      management_price = #{record.managementPrice,jdbcType=VARCHAR},
      max_layer = #{record.maxLayer,jdbcType=INTEGER},
      in_time = #{record.inTime,jdbcType=BIGINT},
      sign_elevator_num = #{record.signElevatorNum,jdbcType=INTEGER},
      management_leader = #{record.managementLeader,jdbcType=VARCHAR},
      management_leader_phone = #{record.managementLeaderPhone,jdbcType=VARCHAR},
      addtime = #{record.addtime,jdbcType=INTEGER},
      addman = #{record.addman,jdbcType=VARCHAR},
      uptime = #{record.uptime,jdbcType=INTEGER},
      upman = #{record.upman,jdbcType=VARCHAR},
      passtime = #{record.passtime,jdbcType=INTEGER},
      passman = #{record.passman,jdbcType=VARCHAR},
      position_lng = #{record.positionLng,jdbcType=DOUBLE},
      position_lat = #{record.positionLat,jdbcType=DOUBLE},
      img = #{record.img,jdbcType=VARCHAR},
      expiration_time = #{record.expirationTime,jdbcType=BIGINT},
      parking_num = #{record.parkingNum,jdbcType=INTEGER},
      parking_price = #{record.parkingPrice,jdbcType=VARCHAR},
      cover_num = #{record.coverNum,jdbcType=INTEGER},
      network_type = #{record.networkType,jdbcType=VARCHAR},
      elevator_num = #{record.elevatorNum,jdbcType=INTEGER},
      min_storey = #{record.minStorey,jdbcType=INTEGER},
      max_storey = #{record.maxStorey,jdbcType=INTEGER},
      total_people = #{record.totalPeople,jdbcType=INTEGER},
      enterprise_num = #{record.enterpriseNum,jdbcType=INTEGER},
      visitors_flowrate = #{record.visitorsFlowrate,jdbcType=INTEGER},
      bo_up_price = #{record.boUpPrice,jdbcType=VARCHAR},
      bo_down_price = #{record.boDownPrice,jdbcType=VARCHAR},
      sign_time = #{record.signTime,jdbcType=VARCHAR},
      building_area = #{record.buildingArea,jdbcType=INTEGER},
      contract_num = #{record.contractNum,jdbcType=VARCHAR},
      remark = #{record.remark,jdbcType=VARCHAR},
      city_code = #{record.cityCode,jdbcType=VARCHAR},
      area_code = #{record.areaCode,jdbcType=VARCHAR},
      province_code = #{record.provinceCode,jdbcType=VARCHAR},
      acreage = #{record.acreage,jdbcType=VARCHAR},
      cubage_rate = #{record.cubageRate,jdbcType=VARCHAR},
      greening_rate = #{record.greeningRate,jdbcType=VARCHAR},
      building_type = #{record.buildingType,jdbcType=VARCHAR},
      overground_parking_num = #{record.overgroundParkingNum,jdbcType=INTEGER},
      charging_pile_num = #{record.chargingPileNum,jdbcType=INTEGER},
      developer_name = #{record.developerName,jdbcType=VARCHAR},
      characteristic = #{record.characteristic,jdbcType=VARCHAR},
      deal_date = #{record.dealDate,jdbcType=INTEGER},
      mix_img = #{record.mixImg,jdbcType=VARCHAR},
      developers_name = #{record.developersName,jdbcType=VARCHAR},
      competitive_media = #{record.competitiveMedia,jdbcType=LONGVARCHAR}
    <if test="_parameter != null" >
      <include refid="Update_By_Example_Where_Clause" />
    </if>
  </update>
  <update id="updateByExample" parameterType="map" >
    update ssp_premises
    set primary_id = #{record.primaryId,jdbcType=INTEGER},
      uu_id = #{record.uuId,jdbcType=VARCHAR},
      id = #{record.id,jdbcType=BIGINT},
      name = #{record.name,jdbcType=VARCHAR},
      developer = #{record.developer,jdbcType=VARCHAR},
      developer_id = #{record.developerId,jdbcType=INTEGER},
      maintainer = #{record.maintainer,jdbcType=VARCHAR},
      maintainer_id = #{record.maintainerId,jdbcType=INTEGER},
      status = #{record.status,jdbcType=CHAR},
      type = #{record.type,jdbcType=CHAR},
      city = #{record.city,jdbcType=INTEGER},
      area = #{record.area,jdbcType=INTEGER},
      management = #{record.management,jdbcType=VARCHAR},
      build_num = #{record.buildNum,jdbcType=INTEGER},
      house_num = #{record.houseNum,jdbcType=INTEGER},
      in_house_rate = #{record.inHouseRate,jdbcType=REAL},
      unit_num = #{record.unitNum,jdbcType=INTEGER},
      address = #{record.address,jdbcType=VARCHAR},
      accurate_price = #{record.accuratePrice,jdbcType=INTEGER},
      house_price = #{record.housePrice,jdbcType=VARCHAR},
      house_price_name = #{record.housePriceName,jdbcType=VARCHAR},
      rent_price = #{record.rentPrice,jdbcType=VARCHAR},
      management_price = #{record.managementPrice,jdbcType=VARCHAR},
      max_layer = #{record.maxLayer,jdbcType=INTEGER},
      in_time = #{record.inTime,jdbcType=BIGINT},
      sign_elevator_num = #{record.signElevatorNum,jdbcType=INTEGER},
      management_leader = #{record.managementLeader,jdbcType=VARCHAR},
      management_leader_phone = #{record.managementLeaderPhone,jdbcType=VARCHAR},
      addtime = #{record.addtime,jdbcType=INTEGER},
      addman = #{record.addman,jdbcType=VARCHAR},
      uptime = #{record.uptime,jdbcType=INTEGER},
      upman = #{record.upman,jdbcType=VARCHAR},
      passtime = #{record.passtime,jdbcType=INTEGER},
      passman = #{record.passman,jdbcType=VARCHAR},
      position_lng = #{record.positionLng,jdbcType=DOUBLE},
      position_lat = #{record.positionLat,jdbcType=DOUBLE},
      img = #{record.img,jdbcType=VARCHAR},
      expiration_time = #{record.expirationTime,jdbcType=BIGINT},
      parking_num = #{record.parkingNum,jdbcType=INTEGER},
      parking_price = #{record.parkingPrice,jdbcType=VARCHAR},
      cover_num = #{record.coverNum,jdbcType=INTEGER},
      network_type = #{record.networkType,jdbcType=VARCHAR},
      elevator_num = #{record.elevatorNum,jdbcType=INTEGER},
      min_storey = #{record.minStorey,jdbcType=INTEGER},
      max_storey = #{record.maxStorey,jdbcType=INTEGER},
      total_people = #{record.totalPeople,jdbcType=INTEGER},
      enterprise_num = #{record.enterpriseNum,jdbcType=INTEGER},
      visitors_flowrate = #{record.visitorsFlowrate,jdbcType=INTEGER},
      bo_up_price = #{record.boUpPrice,jdbcType=VARCHAR},
      bo_down_price = #{record.boDownPrice,jdbcType=VARCHAR},
      sign_time = #{record.signTime,jdbcType=VARCHAR},
      building_area = #{record.buildingArea,jdbcType=INTEGER},
      contract_num = #{record.contractNum,jdbcType=VARCHAR},
      remark = #{record.remark,jdbcType=VARCHAR},
      city_code = #{record.cityCode,jdbcType=VARCHAR},
      area_code = #{record.areaCode,jdbcType=VARCHAR},
      province_code = #{record.provinceCode,jdbcType=VARCHAR},
      acreage = #{record.acreage,jdbcType=VARCHAR},
      cubage_rate = #{record.cubageRate,jdbcType=VARCHAR},
      greening_rate = #{record.greeningRate,jdbcType=VARCHAR},
      building_type = #{record.buildingType,jdbcType=VARCHAR},
      overground_parking_num = #{record.overgroundParkingNum,jdbcType=INTEGER},
      charging_pile_num = #{record.chargingPileNum,jdbcType=INTEGER},
      developer_name = #{record.developerName,jdbcType=VARCHAR},
      characteristic = #{record.characteristic,jdbcType=VARCHAR},
      deal_date = #{record.dealDate,jdbcType=INTEGER},
      mix_img = #{record.mixImg,jdbcType=VARCHAR},
      developers_name = #{record.developersName,jdbcType=VARCHAR}
    <if test="_parameter != null" >
      <include refid="Update_By_Example_Where_Clause" />
    </if>
  </update>
  <update id="updateByPrimaryKeySelective" parameterType="com.business.dao.entity.projectEntity.SspPremises" >
    update ssp_premises
    <set >
      <if test="uuId != null" >
        uu_id = #{uuId,jdbcType=VARCHAR},
      </if>
      <if test="id != null" >
        id = #{id,jdbcType=BIGINT},
      </if>
      <if test="name != null" >
        name = #{name,jdbcType=VARCHAR},
      </if>
      <if test="developer != null" >
        developer = #{developer,jdbcType=VARCHAR},
      </if>
      <if test="developerId != null" >
        developer_id = #{developerId,jdbcType=INTEGER},
      </if>
      <if test="maintainer != null" >
        maintainer = #{maintainer,jdbcType=VARCHAR},
      </if>
      <if test="maintainerId != null" >
        maintainer_id = #{maintainerId,jdbcType=INTEGER},
      </if>
      <if test="status != null" >
        status = #{status,jdbcType=CHAR},
      </if>
      <if test="type != null" >
        type = #{type,jdbcType=CHAR},
      </if>
      <if test="city != null" >
        city = #{city,jdbcType=INTEGER},
      </if>
      <if test="area != null" >
        area = #{area,jdbcType=INTEGER},
      </if>
      <if test="management != null" >
        management = #{management,jdbcType=VARCHAR},
      </if>
      <if test="buildNum != null" >
        build_num = #{buildNum,jdbcType=INTEGER},
      </if>
      <if test="houseNum != null" >
        house_num = #{houseNum,jdbcType=INTEGER},
      </if>
      <if test="inHouseRate != null" >
        in_house_rate = #{inHouseRate,jdbcType=REAL},
      </if>
      <if test="unitNum != null" >
        unit_num = #{unitNum,jdbcType=INTEGER},
      </if>
      <if test="address != null" >
        address = #{address,jdbcType=VARCHAR},
      </if>
      <if test="accuratePrice != null" >
        accurate_price = #{accuratePrice,jdbcType=INTEGER},
      </if>
      <if test="housePrice != null" >
        house_price = #{housePrice,jdbcType=VARCHAR},
      </if>
      <if test="housePriceName != null" >
        house_price_name = #{housePriceName,jdbcType=VARCHAR},
      </if>
      <if test="rentPrice != null" >
        rent_price = #{rentPrice,jdbcType=VARCHAR},
      </if>
      <if test="managementPrice != null" >
        management_price = #{managementPrice,jdbcType=VARCHAR},
      </if>
      <if test="maxLayer != null" >
        max_layer = #{maxLayer,jdbcType=INTEGER},
      </if>
      <if test="inTime != null" >
        in_time = #{inTime,jdbcType=BIGINT},
      </if>
      <if test="signElevatorNum != null" >
        sign_elevator_num = #{signElevatorNum,jdbcType=INTEGER},
      </if>
      <if test="managementLeader != null" >
        management_leader = #{managementLeader,jdbcType=VARCHAR},
      </if>
      <if test="managementLeaderPhone != null" >
        management_leader_phone = #{managementLeaderPhone,jdbcType=VARCHAR},
      </if>
      <if test="addtime != null" >
        addtime = #{addtime,jdbcType=INTEGER},
      </if>
      <if test="addman != null" >
        addman = #{addman,jdbcType=VARCHAR},
      </if>
      <if test="uptime != null" >
        uptime = #{uptime,jdbcType=INTEGER},
      </if>
      <if test="upman != null" >
        upman = #{upman,jdbcType=VARCHAR},
      </if>
      <if test="passtime != null" >
        passtime = #{passtime,jdbcType=INTEGER},
      </if>
      <if test="passman != null" >
        passman = #{passman,jdbcType=VARCHAR},
      </if>
      <if test="positionLng != null" >
        position_lng = #{positionLng,jdbcType=DOUBLE},
      </if>
      <if test="positionLat != null" >
        position_lat = #{positionLat,jdbcType=DOUBLE},
      </if>
      <if test="img != null" >
        img = #{img,jdbcType=VARCHAR},
      </if>
      <if test="expirationTime != null" >
        expiration_time = #{expirationTime,jdbcType=BIGINT},
      </if>
      <if test="parkingNum != null" >
        parking_num = #{parkingNum,jdbcType=INTEGER},
      </if>
      <if test="parkingPrice != null" >
        parking_price = #{parkingPrice,jdbcType=VARCHAR},
      </if>
      <if test="coverNum != null" >
        cover_num = #{coverNum,jdbcType=INTEGER},
      </if>
      <if test="networkType != null" >
        network_type = #{networkType,jdbcType=VARCHAR},
      </if>
      <if test="elevatorNum != null" >
        elevator_num = #{elevatorNum,jdbcType=INTEGER},
      </if>
      <if test="minStorey != null" >
        min_storey = #{minStorey,jdbcType=INTEGER},
      </if>
      <if test="maxStorey != null" >
        max_storey = #{maxStorey,jdbcType=INTEGER},
      </if>
      <if test="totalPeople != null" >
        total_people = #{totalPeople,jdbcType=INTEGER},
      </if>
      <if test="enterpriseNum != null" >
        enterprise_num = #{enterpriseNum,jdbcType=INTEGER},
      </if>
      <if test="visitorsFlowrate != null" >
        visitors_flowrate = #{visitorsFlowrate,jdbcType=INTEGER},
      </if>
      <if test="boUpPrice != null" >
        bo_up_price = #{boUpPrice,jdbcType=VARCHAR},
      </if>
      <if test="boDownPrice != null" >
        bo_down_price = #{boDownPrice,jdbcType=VARCHAR},
      </if>
      <if test="signTime != null" >
        sign_time = #{signTime,jdbcType=VARCHAR},
      </if>
      <if test="buildingArea != null" >
        building_area = #{buildingArea,jdbcType=INTEGER},
      </if>
      <if test="contractNum != null" >
        contract_num = #{contractNum,jdbcType=VARCHAR},
      </if>
      <if test="remark != null" >
        remark = #{remark,jdbcType=VARCHAR},
      </if>
      <if test="cityCode != null" >
        city_code = #{cityCode,jdbcType=VARCHAR},
      </if>
      <if test="areaCode != null" >
        area_code = #{areaCode,jdbcType=VARCHAR},
      </if>
      <if test="provinceCode != null" >
        province_code = #{provinceCode,jdbcType=VARCHAR},
      </if>
      <if test="acreage != null" >
        acreage = #{acreage,jdbcType=VARCHAR},
      </if>
      <if test="cubageRate != null" >
        cubage_rate = #{cubageRate,jdbcType=VARCHAR},
      </if>
      <if test="greeningRate != null" >
        greening_rate = #{greeningRate,jdbcType=VARCHAR},
      </if>
      <if test="buildingType != null" >
        building_type = #{buildingType,jdbcType=VARCHAR},
      </if>
      <if test="overgroundParkingNum != null" >
        overground_parking_num = #{overgroundParkingNum,jdbcType=INTEGER},
      </if>
      <if test="chargingPileNum != null" >
        charging_pile_num = #{chargingPileNum,jdbcType=INTEGER},
      </if>
      <if test="developerName != null" >
        developer_name = #{developerName,jdbcType=VARCHAR},
      </if>
      <if test="characteristic != null" >
        characteristic = #{characteristic,jdbcType=VARCHAR},
      </if>
      <if test="dealDate != null" >
        deal_date = #{dealDate,jdbcType=INTEGER},
      </if>
      <if test="mixImg != null" >
        mix_img = #{mixImg,jdbcType=VARCHAR},
      </if>
      <if test="developersName != null" >
        developers_name = #{developersName,jdbcType=VARCHAR},
      </if>
      <if test="competitiveMedia != null" >
        competitive_media = #{competitiveMedia,jdbcType=LONGVARCHAR},
      </if>
    </set>
    where primary_id = #{primaryId,jdbcType=INTEGER}
  </update>
  <update id="updateByPrimaryKeyWithBLOBs" parameterType="com.business.dao.entity.projectEntity.SspPremises" >
    update ssp_premises
    set uu_id = #{uuId,jdbcType=VARCHAR},
      id = #{id,jdbcType=BIGINT},
      name = #{name,jdbcType=VARCHAR},
      developer = #{developer,jdbcType=VARCHAR},
      developer_id = #{developerId,jdbcType=INTEGER},
      maintainer = #{maintainer,jdbcType=VARCHAR},
      maintainer_id = #{maintainerId,jdbcType=INTEGER},
      status = #{status,jdbcType=CHAR},
      type = #{type,jdbcType=CHAR},
      city = #{city,jdbcType=INTEGER},
      area = #{area,jdbcType=INTEGER},
      management = #{management,jdbcType=VARCHAR},
      build_num = #{buildNum,jdbcType=INTEGER},
      house_num = #{houseNum,jdbcType=INTEGER},
      in_house_rate = #{inHouseRate,jdbcType=REAL},
      unit_num = #{unitNum,jdbcType=INTEGER},
      address = #{address,jdbcType=VARCHAR},
      accurate_price = #{accuratePrice,jdbcType=INTEGER},
      house_price = #{housePrice,jdbcType=VARCHAR},
      house_price_name = #{housePriceName,jdbcType=VARCHAR},
      rent_price = #{rentPrice,jdbcType=VARCHAR},
      management_price = #{managementPrice,jdbcType=VARCHAR},
      max_layer = #{maxLayer,jdbcType=INTEGER},
      in_time = #{inTime,jdbcType=BIGINT},
      sign_elevator_num = #{signElevatorNum,jdbcType=INTEGER},
      management_leader = #{managementLeader,jdbcType=VARCHAR},
      management_leader_phone = #{managementLeaderPhone,jdbcType=VARCHAR},
      addtime = #{addtime,jdbcType=INTEGER},
      addman = #{addman,jdbcType=VARCHAR},
      uptime = #{uptime,jdbcType=INTEGER},
      upman = #{upman,jdbcType=VARCHAR},
      passtime = #{passtime,jdbcType=INTEGER},
      passman = #{passman,jdbcType=VARCHAR},
      position_lng = #{positionLng,jdbcType=DOUBLE},
      position_lat = #{positionLat,jdbcType=DOUBLE},
      img = #{img,jdbcType=VARCHAR},
      expiration_time = #{expirationTime,jdbcType=BIGINT},
      parking_num = #{parkingNum,jdbcType=INTEGER},
      parking_price = #{parkingPrice,jdbcType=VARCHAR},
      cover_num = #{coverNum,jdbcType=INTEGER},
      network_type = #{networkType,jdbcType=VARCHAR},
      elevator_num = #{elevatorNum,jdbcType=INTEGER},
      min_storey = #{minStorey,jdbcType=INTEGER},
      max_storey = #{maxStorey,jdbcType=INTEGER},
      total_people = #{totalPeople,jdbcType=INTEGER},
      enterprise_num = #{enterpriseNum,jdbcType=INTEGER},
      visitors_flowrate = #{visitorsFlowrate,jdbcType=INTEGER},
      bo_up_price = #{boUpPrice,jdbcType=VARCHAR},
      bo_down_price = #{boDownPrice,jdbcType=VARCHAR},
      sign_time = #{signTime,jdbcType=VARCHAR},
      building_area = #{buildingArea,jdbcType=INTEGER},
      contract_num = #{contractNum,jdbcType=VARCHAR},
      remark = #{remark,jdbcType=VARCHAR},
      city_code = #{cityCode,jdbcType=VARCHAR},
      area_code = #{areaCode,jdbcType=VARCHAR},
      province_code = #{provinceCode,jdbcType=VARCHAR},
      acreage = #{acreage,jdbcType=VARCHAR},
      cubage_rate = #{cubageRate,jdbcType=VARCHAR},
      greening_rate = #{greeningRate,jdbcType=VARCHAR},
      building_type = #{buildingType,jdbcType=VARCHAR},
      overground_parking_num = #{overgroundParkingNum,jdbcType=INTEGER},
      charging_pile_num = #{chargingPileNum,jdbcType=INTEGER},
      developer_name = #{developerName,jdbcType=VARCHAR},
      characteristic = #{characteristic,jdbcType=VARCHAR},
      deal_date = #{dealDate,jdbcType=INTEGER},
      mix_img = #{mixImg,jdbcType=VARCHAR},
      developers_name = #{developersName,jdbcType=VARCHAR},
      competitive_media = #{competitiveMedia,jdbcType=LONGVARCHAR}
    where primary_id = #{primaryId,jdbcType=INTEGER}
  </update>
  <update id="updateByPrimaryKey" parameterType="com.business.dao.entity.projectEntity.SspPremises" >
    update ssp_premises
    set uu_id = #{uuId,jdbcType=VARCHAR},
      id = #{id,jdbcType=BIGINT},
      name = #{name,jdbcType=VARCHAR},
      developer = #{developer,jdbcType=VARCHAR},
      developer_id = #{developerId,jdbcType=INTEGER},
      maintainer = #{maintainer,jdbcType=VARCHAR},
      maintainer_id = #{maintainerId,jdbcType=INTEGER},
      status = #{status,jdbcType=CHAR},
      type = #{type,jdbcType=CHAR},
      city = #{city,jdbcType=INTEGER},
      area = #{area,jdbcType=INTEGER},
      management = #{management,jdbcType=VARCHAR},
      build_num = #{buildNum,jdbcType=INTEGER},
      house_num = #{houseNum,jdbcType=INTEGER},
      in_house_rate = #{inHouseRate,jdbcType=REAL},
      unit_num = #{unitNum,jdbcType=INTEGER},
      address = #{address,jdbcType=VARCHAR},
      accurate_price = #{accuratePrice,jdbcType=INTEGER},
      house_price = #{housePrice,jdbcType=VARCHAR},
      house_price_name = #{housePriceName,jdbcType=VARCHAR},
      rent_price = #{rentPrice,jdbcType=VARCHAR},
      management_price = #{managementPrice,jdbcType=VARCHAR},
      max_layer = #{maxLayer,jdbcType=INTEGER},
      in_time = #{inTime,jdbcType=BIGINT},
      sign_elevator_num = #{signElevatorNum,jdbcType=INTEGER},
      management_leader = #{managementLeader,jdbcType=VARCHAR},
      management_leader_phone = #{managementLeaderPhone,jdbcType=VARCHAR},
      addtime = #{addtime,jdbcType=INTEGER},
      addman = #{addman,jdbcType=VARCHAR},
      uptime = #{uptime,jdbcType=INTEGER},
      upman = #{upman,jdbcType=VARCHAR},
      passtime = #{passtime,jdbcType=INTEGER},
      passman = #{passman,jdbcType=VARCHAR},
      position_lng = #{positionLng,jdbcType=DOUBLE},
      position_lat = #{positionLat,jdbcType=DOUBLE},
      img = #{img,jdbcType=VARCHAR},
      expiration_time = #{expirationTime,jdbcType=BIGINT},
      parking_num = #{parkingNum,jdbcType=INTEGER},
      parking_price = #{parkingPrice,jdbcType=VARCHAR},
      cover_num = #{coverNum,jdbcType=INTEGER},
      network_type = #{networkType,jdbcType=VARCHAR},
      elevator_num = #{elevatorNum,jdbcType=INTEGER},
      min_storey = #{minStorey,jdbcType=INTEGER},
      max_storey = #{maxStorey,jdbcType=INTEGER},
      total_people = #{totalPeople,jdbcType=INTEGER},
      enterprise_num = #{enterpriseNum,jdbcType=INTEGER},
      visitors_flowrate = #{visitorsFlowrate,jdbcType=INTEGER},
      bo_up_price = #{boUpPrice,jdbcType=VARCHAR},
      bo_down_price = #{boDownPrice,jdbcType=VARCHAR},
      sign_time = #{signTime,jdbcType=VARCHAR},
      building_area = #{buildingArea,jdbcType=INTEGER},
      contract_num = #{contractNum,jdbcType=VARCHAR},
      remark = #{remark,jdbcType=VARCHAR},
      city_code = #{cityCode,jdbcType=VARCHAR},
      area_code = #{areaCode,jdbcType=VARCHAR},
      province_code = #{provinceCode,jdbcType=VARCHAR},
      acreage = #{acreage,jdbcType=VARCHAR},
      cubage_rate = #{cubageRate,jdbcType=VARCHAR},
      greening_rate = #{greeningRate,jdbcType=VARCHAR},
      building_type = #{buildingType,jdbcType=VARCHAR},
      overground_parking_num = #{overgroundParkingNum,jdbcType=INTEGER},
      charging_pile_num = #{chargingPileNum,jdbcType=INTEGER},
      developer_name = #{developerName,jdbcType=VARCHAR},
      characteristic = #{characteristic,jdbcType=VARCHAR},
      deal_date = #{dealDate,jdbcType=INTEGER},
      mix_img = #{mixImg,jdbcType=VARCHAR},
      developers_name = #{developersName,jdbcType=VARCHAR}
    where primary_id = #{primaryId,jdbcType=INTEGER}
  </update>
</mapper>